{
  "title": "PaperScore Metadata",
  "type": "object",
  "properties": {
    "name": {
      "type": "string",
      "description": "A name for Paper NFT could be - e.g. Paper Title"
    },
    "decimals": {
      "type": "integer",
      "description": "0"
    },
    "description": {
      "type": "string",
      "description": "A description about Paper provided by PaperScore"
    },
    "image": {
      "type": "string",
      "description": "A URI pointing to a resource with mime type image/* representing the asset to which this token represents. Consider making any images at a width between 320 and 1080 pixels and aspect ratio between 1.91:1 and 4:5 inclusive."
    },
    "properties": {
      "type": "object",
      "description": "Arbitrary properties. Values may be strings, numbers, object or arrays."
    }
  }
}
